video_background_estimation/EstimateBackground.py
video_background_estimation/__init__.py
video_background_estimation-0.1.4.dist-info/LICENSE
video_background_estimation-0.1.4.dist-info/METADATA
video_background_estimation-0.1.4.dist-info/WHEEL
video_background_estimation-0.1.4.dist-info/RECORD
