Metadata-Version: 2.1
Name: video-background-estimation
Version: 0.1.4
Summary: background estimation based on simple techniques
Home-page: https://github.com/rajesh-bhat/video_background_estimation
License: MIT
Keywords: video background estimation,background extraction from video
Author: Rajesh Shreedhar Bhat
Author-email: rajeshbht19@gmail.com
Requires-Python: >=3.8,<4.0
Classifier: License :: OSI Approved :: MIT License
Classifier: Programming Language :: Python :: 3
Classifier: Programming Language :: Python :: 3.8
Classifier: Programming Language :: Python :: 3.9
Classifier: Programming Language :: Python :: 3.10
Classifier: Programming Language :: Python :: 3.11
Requires-Dist: opencv-python (>=4.7.0.68,<5.0.0.0)
Requires-Dist: tqdm (>=4.64.1,<5.0.0)
Project-URL: Repository, https://github.com/rajesh-bhat/video_background_estimation
